example.py
test_gh_action_test/__init__.py
test_gh_action_test/admin.py
test_gh_action_test/audit.py
test_gh_action_test/cord.py
test_gh_action_test/datastore.py
test_gh_action_test/encryption.py
test_gh_action_test/identities.py
test_gh_action_test/integration_app.py
test_gh_action_test/integration_cloud.py
test_gh_action_test/integration_code_repository.py
test_gh_action_test/integration_datahub.py
test_gh_action_test/integration_external_api.py
test_gh_action_test/integration_github.py
test_gh_action_test/integration_incident.py
test_gh_action_test/integration_kms.py
test_gh_action_test/integration_log.py
test_gh_action_test/integration_slack.py
test_gh_action_test/integration_sso.py
test_gh_action_test/inventory.py
test_gh_action_test/metrics.py
test_gh_action_test/native_user.py
test_gh_action_test/outputs.py
test_gh_action_test/policies.py
test_gh_action_test/registry.py
test_gh_action_test/satellite.py
test_gh_action_test/search.py
test_gh_action_test/sidecar.py
test_gh_action_test/work_os.py
test_gh_action_test/gen/admin/v1/__init__.py
test_gh_action_test/gen/admin/v1/admin_pb2.py
test_gh_action_test/gen/admin/v1/admin_pb2.pyi
test_gh_action_test/gen/admin/v1/admin_pb2_grpc.py
test_gh_action_test/gen/admin/v1/audit_pb2.py
test_gh_action_test/gen/admin/v1/audit_pb2.pyi
test_gh_action_test/gen/admin/v1/audit_pb2_grpc.py
test_gh_action_test/gen/admin/v1/cord_pb2.py
test_gh_action_test/gen/admin/v1/cord_pb2.pyi
test_gh_action_test/gen/admin/v1/cord_pb2_grpc.py
test_gh_action_test/gen/admin/v1/datastore_pb2.py
test_gh_action_test/gen/admin/v1/datastore_pb2.pyi
test_gh_action_test/gen/admin/v1/datastore_pb2_grpc.py
test_gh_action_test/gen/admin/v1/encryption_pb2.py
test_gh_action_test/gen/admin/v1/encryption_pb2.pyi
test_gh_action_test/gen/admin/v1/encryption_pb2_grpc.py
test_gh_action_test/gen/admin/v1/identities_pb2.py
test_gh_action_test/gen/admin/v1/identities_pb2.pyi
test_gh_action_test/gen/admin/v1/identities_pb2_grpc.py
test_gh_action_test-1.0.5.dist-info/LICENSE
test_gh_action_test-1.0.5.dist-info/METADATA
test_gh_action_test-1.0.5.dist-info/WHEEL
test_gh_action_test-1.0.5.dist-info/top_level.txt
test_gh_action_test-1.0.5.dist-info/RECORD
