Metadata-Version: 2.1
Name: test-gh-action-test
Version: 1.0.5
Summary: Test
Author-email: Farid <faridwajdi05@gmail.com>
License: MIT License
Project-URL: Homepage, https://github.com/wajdifarid
Classifier: Programming Language :: Python :: 3
Classifier: License :: OSI Approved :: MIT License
Classifier: Operating System :: OS Independent
Requires-Python: >=3.7
License-File: LICENSE
Requires-Dist: requests (>=2.26.0)
